CSC201UT/BinaryHeap.py
CSC201UT/BinaryTree.py
CSC201UT/Deque.py
CSC201UT/MSDie.py
CSC201UT/MazeUtils.py
CSC201UT/Node.py
CSC201UT/OrderedBinaryTree.py
CSC201UT/OrderedList.py
CSC201UT/Sorts.py
CSC201UT/Stack.py
CSC201UT/Trees.py
CSC201UT/UnorderedList.py
CSC201UT/__init__.py
CSC201UT/circuits.py
CSC201UT-1.3.dist-info/LICENSE.md
CSC201UT-1.3.dist-info/METADATA
CSC201UT-1.3.dist-info/WHEEL
CSC201UT-1.3.dist-info/top_level.txt
CSC201UT-1.3.dist-info/RECORD
